model_sentinel/__init__.py
model_sentinel/cli.py
model_sentinel/gui/__init__.py
model_sentinel/gui/components.py
model_sentinel/gui/gui.py
model_sentinel/gui/utils.py
model_sentinel/target/__init__.py
model_sentinel/target/base.py
model_sentinel/target/hf.py
model_sentinel/target/local.py
model_sentinel/verify/__init__.py
model_sentinel/verify/errors.py
model_sentinel/verify/metadata.py
model_sentinel/verify/session.py
model_sentinel/verify/storage.py
model_sentinel/verify/verify.py
model_sentinel-0.4.0.dist-info/METADATA
model_sentinel-0.4.0.dist-info/WHEEL
model_sentinel-0.4.0.dist-info/entry_points.txt
model_sentinel-0.4.0.dist-info/licenses/LICENSE
model_sentinel-0.4.0.dist-info/RECORD
