Metadata-Version: 2.4
Name: model-sentinel
Version: 0.4.0
Summary: A security verification tool for AI model scripts - Detects and verifies changes in Python files of AI models
Project-URL: Homepage, https://github.com/ryomo/model-sentinel
Project-URL: Repository, https://github.com/ryomo/model-sentinel
Project-URL: Issues, https://github.com/ryomo/model-sentinel/issues
Project-URL: Documentation, https://github.com/ryomo/model-sentinel#readme
Author-email: Ryo Moriwaki <ryomo@duck.com>
Maintainer-email: Ryo Moriwaki <ryomo@duck.com>
License: MIT
License-File: LICENSE
Keywords: ai,code-analysis,huggingface,machine-learning,malware-detection,model-verification,security
Classifier: Development Status :: 3 - Alpha
Classifier: Intended Audience :: Developers
Classifier: Intended Audience :: Science/Research
Classifier: License :: OSI Approved :: MIT License
Classifier: Operating System :: OS Independent
Classifier: Programming Language :: Python :: 3
Classifier: Programming Language :: Python :: 3.10
Classifier: Programming Language :: Python :: 3.11
Classifier: Programming Language :: Python :: 3.12
Classifier: Topic :: Scientific/Engineering :: Artificial Intelligence
Classifier: Topic :: Security
Classifier: Topic :: Software Development :: Quality Assurance
Classifier: Topic :: Software Development :: Testing
Requires-Python: >=3.10
Requires-Dist: huggingface-hub>=0.33.0
Requires-Dist: platformdirs>=4.3.8
Provides-Extra: gui
Requires-Dist: gradio>=5.37.0; extra == 'gui'
